{
  "classname": null,
  "name": null,
  "animation": {
    "classname": null,
    "name": "AnimationManager",
    "actionlist": []
  },
  "dataScale": 1,
  "designHeight": 640,
  "designWidth": 1136,
  "textures": [],
  "texturesPng": [
    "res2/nan.png",
    "res2/meng.png",
    "res2/info_bg.png",
    "res2/btn_close.png",
    "res2/thumb_bg.png",
    "res2/thumb.png"
  ],
  "version": "1.6.0.0",
  "widgetTree": {
    "classname": "Panel",
    "name": null,
    "children": [
      {
        "classname": "ImageView",
        "name": null,
        "children": [],
        "options": {
          "__type": "ImageViewSurrogate:#EditorCommon.JsonModel.Component.GUI",
          "classname": "ImageView",
          "name": "label_sex",
          "ZOrder": 5,
          "actiontag": 39473680,
          "anchorPointX": 0.5,
          "anchorPointY": 0.5,
          "classType": "CocoStudio.EngineAdapterWrap.CSImageView",
          "colorB": 255,
          "colorG": 255,
          "colorR": 255,
          "customProperty": "",
          "flipX": false,
          "flipY": false,
          "height": 27,
          "ignoreSize": true,
          "layoutParameter": null,
          "opacity": 255,
          "positionPercentX": 0.47623238,
          "positionPercentY": 0.5640625,
          "positionType": 0,
          "rotation": 0,
          "scaleX": 1,
          "scaleY": 1,
          "sizePercentX": 0.0237676054,
          "sizePercentY": 0.0421875,
          "sizeType": 0,
          "tag": 943,
          "touchAble": false,
          "useMergedTexture": false,
          "visible": true,
          "width": 27,
          "x": 541,
          "y": 361,
          "capInsetsHeight": 1,
          "capInsetsWidth": 1,
          "capInsetsX": 0,
          "capInsetsY": 0,
          "fileName": null,
          "fileNameData": {
            "path": "res2/nan.png",
            "plistFile": "",
            "resourceType": 0
          },
          "scale9Enable": false,
          "scale9Height": 27,
          "scale9Width": 27
        }
      },
      {
        "classname": "ImageView",
        "name": null,
        "children": [],
        "options": {
          "__type": "ImageViewSurrogate:#EditorCommon.JsonModel.Component.GUI",
          "classname": "ImageView",
          "name": "Image_1",
          "ZOrder": 0,
          "actiontag": 45450086,
          "anchorPointX": 0.5,
          "anchorPointY": 0.5,
          "classType": "CocoStudio.EngineAdapterWrap.CSImageView",
          "colorB": 255,
          "colorG": 255,
          "colorR": 255,
          "customProperty": "",
          "flipX": false,
          "flipY": false,
          "height": 640,
          "ignoreSize": true,
          "layoutParameter": null,
          "opacity": 57,
          "positionPercentX": 0.499119729,
          "positionPercentY": 0.5046875,
          "positionType": 0,
          "rotation": 0,
          "scaleX": 1.02543,
          "scaleY": 1.05208325,
          "sizePercentX": 1,
          "sizePercentY": 1,
          "sizeType": 0,
          "tag": 938,
          "touchAble": false,
          "useMergedTexture": false,
          "visible": true,
          "width": 1136,
          "x": 567,
          "y": 323,
          "capInsetsHeight": 1,
          "capInsetsWidth": 1,
          "capInsetsX": 0,
          "capInsetsY": 0,
          "fileName": null,
          "fileNameData": {
            "path": "res2/meng.png",
            "plistFile": "",
            "resourceType": 0
          },
          "scale9Enable": false,
          "scale9Height": 640,
          "scale9Width": 1136
        }
      },
      {
        "classname": "ImageView",
        "name": null,
        "children": [
          {
            "classname": "Button",
            "name": null,
            "children": [],
            "options": {
              "__type": "ButtonSurrogate:#EditorCommon.JsonModel.Component.GUI",
              "classname": "Button",
              "name": "btn_close",
              "ZOrder": 0,
              "actiontag": 63469331,
              "anchorPointX": 0.5,
              "anchorPointY": 0.5,
              "classType": "CocoStudio.EngineAdapterWrap.CSButton",
              "colorB": 255,
              "colorG": 255,
              "colorR": 255,
              "customProperty": "",
              "flipX": false,
              "flipY": false,
              "height": 56,
              "ignoreSize": true,
              "layoutParameter": null,
              "opacity": 255,
              "positionPercentX": 0.460733,
              "positionPercentY": 0.423529416,
              "positionType": 0,
              "rotation": 0,
              "scaleX": 1,
              "scaleY": 1,
              "sizePercentX": 0.146596864,
              "sizePercentY": 0.329411775,
              "sizeType": 0,
              "tag": 940,
              "touchAble": true,
              "useMergedTexture": false,
              "visible": true,
              "width": 56,
              "x": 176,
              "y": 72,
              "capInsetsHeight": 1,
              "capInsetsWidth": 1,
              "capInsetsX": 0,
              "capInsetsY": 0,
              "disabled": null,
              "disabledData": {
                "path": null,
                "plistFile": null,
                "resourceType": 0
              },
              "fontName": "微软雅黑",
              "fontSize": 14,
              "fontType": 0,
              "normal": null,
              "normalData": {
                "path": "res2/btn_close.png",
                "plistFile": "",
                "resourceType": 0
              },
              "pressed": null,
              "pressedData": {
                "path": null,
                "plistFile": null,
                "resourceType": 0
              },
              "scale9Enable": false,
              "scale9Height": 56,
              "scale9Width": 56,
              "text": "",
              "textColorB": 255,
              "textColorG": 255,
              "textColorR": 255
            }
          },
          {
            "classname": "ImageView",
            "name": null,
            "children": [],
            "options": {
              "__type": "ImageViewSurrogate:#EditorCommon.JsonModel.Component.GUI",
              "classname": "ImageView",
              "name": "Image_4",
              "ZOrder": 0,
              "actiontag": 37235913,
              "anchorPointX": 0.5,
              "anchorPointY": 0.5,
              "classType": "CocoStudio.EngineAdapterWrap.CSImageView",
              "colorB": 255,
              "colorG": 255,
              "colorR": 255,
              "customProperty": "",
              "flipX": false,
              "flipY": false,
              "height": 77,
              "ignoreSize": true,
              "layoutParameter": null,
              "opacity": 255,
              "positionPercentX": -0.290575922,
              "positionPercentY": 0.105882354,
              "positionType": 0,
              "rotation": 0,
              "scaleX": 1,
              "scaleY": 1,
              "sizePercentX": 0.201570675,
              "sizePercentY": 0.452941179,
              "sizeType": 0,
              "tag": 941,
              "touchAble": false,
              "useMergedTexture": false,
              "visible": true,
              "width": 77,
              "x": -111,
              "y": 18,
              "capInsetsHeight": 1,
              "capInsetsWidth": 1,
              "capInsetsX": 0,
              "capInsetsY": 0,
              "fileName": null,
              "fileNameData": {
                "path": "res2/thumb_bg.png",
                "plistFile": "",
                "resourceType": 0
              },
              "scale9Enable": false,
              "scale9Height": 77,
              "scale9Width": 77
            }
          },
          {
            "classname": "Label",
            "name": null,
            "children": [],
            "options": {
              "__type": "LabelSurrogate:#EditorCommon.JsonModel.Component.GUI",
              "classname": "Label",
              "name": "label_name",
              "ZOrder": 0,
              "actiontag": 63890936,
              "anchorPointX": 0,
              "anchorPointY": 0.49999997,
              "classType": "CocoStudio.EngineAdapterWrap.CSLabel",
              "colorB": 19,
              "colorG": 117,
              "colorR": 140,
              "customProperty": "",
              "flipX": false,
              "flipY": false,
              "height": 30,
              "ignoreSize": true,
              "layoutParameter": null,
              "opacity": 255,
              "positionPercentX": -0.0549738221,
              "positionPercentY": 0.258823544,
              "positionType": 0,
              "rotation": 0,
              "scaleX": 1,
              "scaleY": 1,
              "sizePercentX": 0.159685865,
              "sizePercentY": 0.1764706,
              "sizeType": 0,
              "tag": 944,
              "touchAble": false,
              "useMergedTexture": false,
              "visible": true,
              "width": 61,
              "x": -21,
              "y": 44,
              "areaHeight": 0,
              "areaWidth": 0,
              "fontFile": null,
              "fontName": "微软雅黑",
              "fontSize": 22,
              "hAlignment": 0,
              "text": "Vistor",
              "touchScaleEnable": false,
              "vAlignment": 0
            }
          },
          {
            "classname": "Label",
            "name": null,
            "children": [],
            "options": {
              "__type": "LabelSurrogate:#EditorCommon.JsonModel.Component.GUI",
              "classname": "Label",
              "name": "Label_8",
              "ZOrder": 0,
              "actiontag": 53057107,
              "anchorPointX": 0.5,
              "anchorPointY": 0.5,
              "classType": "CocoStudio.EngineAdapterWrap.CSLabel",
              "colorB": 3,
              "colorG": 3,
              "colorR": 41,
              "customProperty": "",
              "flipX": false,
              "flipY": false,
              "height": 30,
              "ignoreSize": true,
              "layoutParameter": null,
              "opacity": 255,
              "positionPercentX": -0.112565443,
              "positionPercentY": -0.05882353,
              "positionType": 0,
              "rotation": 0,
              "scaleX": 1,
              "scaleY": 1,
              "sizePercentX": 0.07329843,
              "sizePercentY": 0.1764706,
              "sizeType": 0,
              "tag": 945,
              "touchAble": false,
              "useMergedTexture": false,
              "visible": true,
              "width": 28,
              "x": -43,
              "y": -10,
              "areaHeight": 0,
              "areaWidth": 0,
              "fontFile": null,
              "fontName": "微软雅黑",
              "fontSize": 22,
              "hAlignment": 0,
              "text": "ID:",
              "touchScaleEnable": false,
              "vAlignment": 0
            }
          },
          {
            "classname": "Label",
            "name": null,
            "children": [],
            "options": {
              "__type": "LabelSurrogate:#EditorCommon.JsonModel.Component.GUI",
              "classname": "Label",
              "name": "label_id",
              "ZOrder": 0,
              "actiontag": 30442085,
              "anchorPointX": 0.5,
              "anchorPointY": 0.5,
              "classType": "CocoStudio.EngineAdapterWrap.CSLabel",
              "colorB": 3,
              "colorG": 2,
              "colorR": 28,
              "customProperty": "",
              "flipX": false,
              "flipY": false,
              "height": 30,
              "ignoreSize": true,
              "layoutParameter": null,
              "opacity": 255,
              "positionPercentX": 0.06282722,
              "positionPercentY": -0.05882353,
              "positionType": 0,
              "rotation": 0,
              "scaleX": 1,
              "scaleY": 1,
              "sizePercentX": 0.204188481,
              "sizePercentY": 0.1764706,
              "sizeType": 0,
              "tag": 946,
              "touchAble": false,
              "useMergedTexture": false,
              "visible": true,
              "width": 78,
              "x": 24,
              "y": -10,
              "areaHeight": 0,
              "areaWidth": 0,
              "fontFile": null,
              "fontName": "微软雅黑",
              "fontSize": 22,
              "hAlignment": 0,
              "text": "888888",
              "touchScaleEnable": false,
              "vAlignment": 0
            }
          },
          {
            "classname": "Label",
            "name": null,
            "children": [],
            "options": {
              "__type": "LabelSurrogate:#EditorCommon.JsonModel.Component.GUI",
              "classname": "Label",
              "name": "Label_10",
              "ZOrder": 0,
              "actiontag": 35318547,
              "anchorPointX": 0.5,
              "anchorPointY": 0.5,
              "classType": "CocoStudio.EngineAdapterWrap.CSLabel",
              "colorB": 2,
              "colorG": 2,
              "colorR": 31,
              "customProperty": "",
              "flipX": false,
              "flipY": false,
              "height": 30,
              "ignoreSize": true,
              "layoutParameter": null,
              "opacity": 255,
              "positionPercentX": -0.115183249,
              "positionPercentY": -0.2882353,
              "positionType": 0,
              "rotation": 0,
              "scaleX": 1,
              "scaleY": 1,
              "sizePercentX": 0.06282722,
              "sizePercentY": 0.1764706,
              "sizeType": 0,
              "tag": 947,
              "touchAble": false,
              "useMergedTexture": false,
              "visible": true,
              "width": 24,
              "x": -44,
              "y": -49,
              "areaHeight": 0,
              "areaWidth": 0,
              "fontFile": null,
              "fontName": "微软雅黑",
              "fontSize": 22,
              "hAlignment": 0,
              "text": "IP:",
              "touchScaleEnable": false,
              "vAlignment": 0
            }
          },
          {
            "classname": "Label",
            "name": null,
            "children": [],
            "options": {
              "__type": "LabelSurrogate:#EditorCommon.JsonModel.Component.GUI",
              "classname": "Label",
              "name": "label_ip",
              "ZOrder": 0,
              "actiontag": 32411561,
              "anchorPointX": 0,
              "anchorPointY": 0.5,
              "classType": "CocoStudio.EngineAdapterWrap.CSLabel",
              "colorB": 4,
              "colorG": 4,
              "colorR": 33,
              "customProperty": "",
              "flipX": false,
              "flipY": false,
              "height": 27,
              "ignoreSize": true,
              "layoutParameter": null,
              "opacity": 255,
              "positionPercentX": -0.0392670147,
              "positionPercentY": -0.2882353,
              "positionType": 0,
              "rotation": 0,
              "scaleX": 1,
              "scaleY": 1,
              "sizePercentX": 0.416230381,
              "sizePercentY": 0.158823535,
              "sizeType": 0,
              "tag": 948,
              "touchAble": false,
              "useMergedTexture": false,
              "visible": true,
              "width": 159,
              "x": -15,
              "y": -49,
              "areaHeight": 0,
              "areaWidth": 0,
              "fontFile": null,
              "fontName": "微软雅黑",
              "fontSize": 20,
              "hAlignment": 0,
              "text": "111.111.111.111",
              "touchScaleEnable": false,
              "vAlignment": 0
            }
          }
        ],
        "options": {
          "__type": "ImageViewSurrogate:#EditorCommon.JsonModel.Component.GUI",
          "classname": "ImageView",
          "name": "Image_2",
          "ZOrder": 0,
          "actiontag": 28346915,
          "anchorPointX": 0.5,
          "anchorPointY": 0.5,
          "classType": "CocoStudio.EngineAdapterWrap.CSImageView",
          "colorB": 255,
          "colorG": 255,
          "colorR": 255,
          "customProperty": "",
          "flipX": false,
          "flipY": false,
          "height": 170,
          "ignoreSize": true,
          "layoutParameter": null,
          "opacity": 255,
          "positionPercentX": 0.51584506,
          "positionPercentY": 0.4953125,
          "positionType": 0,
          "rotation": 0,
          "scaleX": 1,
          "scaleY": 1,
          "sizePercentX": 0.33626762,
          "sizePercentY": 0.265625,
          "sizeType": 0,
          "tag": 939,
          "touchAble": false,
          "useMergedTexture": false,
          "visible": true,
          "width": 382,
          "x": 586,
          "y": 317,
          "capInsetsHeight": 1,
          "capInsetsWidth": 1,
          "capInsetsX": 0,
          "capInsetsY": 0,
          "fileName": null,
          "fileNameData": {
            "path": "res2/info_bg.png",
            "plistFile": "",
            "resourceType": 0
          },
          "scale9Enable": false,
          "scale9Height": 170,
          "scale9Width": 382
        }
      },
      {
        "classname": "ImageView",
        "name": null,
        "children": [],
        "options": {
          "__type": "ImageViewSurrogate:#EditorCommon.JsonModel.Component.GUI",
          "classname": "ImageView",
          "name": "headImg",
          "ZOrder": 0,
          "actiontag": 57664431,
          "anchorPointX": 0.5,
          "anchorPointY": 0.5,
          "classType": "CocoStudio.EngineAdapterWrap.CSImageView",
          "colorB": 255,
          "colorG": 255,
          "colorR": 255,
          "customProperty": "",
          "flipX": false,
          "flipY": false,
          "height": 73,
          "ignoreSize": true,
          "layoutParameter": null,
          "opacity": 255,
          "positionPercentX": 0.418035984,
          "positionPercentY": 0.5236111,
          "positionType": 0,
          "rotation": 0,
          "scaleX": 1,
          "scaleY": 1,
          "sizePercentX": 0.0642605647,
          "sizePercentY": 0.1140625,
          "sizeType": 0,
          "tag": 942,
          "touchAble": false,
          "useMergedTexture": false,
          "visible": true,
          "width": 73,
          "x": 474,
          "y": 335,
          "capInsetsHeight": 1,
          "capInsetsWidth": 1,
          "capInsetsX": 0,
          "capInsetsY": 0,
          "fileName": null,
          "fileNameData": {
            "path": "res2/thumb.png",
            "plistFile": "",
            "resourceType": 0
          },
          "scale9Enable": false,
          "scale9Height": 73,
          "scale9Width": 73
        }
      }
    ],
    "options": {
      "__type": "PanelSurrogate:#EditorCommon.JsonModel.Component.GUI",
      "classname": "Panel",
      "name": "Panel_7",
      "ZOrder": 0,
      "actiontag": -1,
      "anchorPointX": 0,
      "anchorPointY": 0,
      "classType": "CocoStudio.EngineAdapterWrap.CSPanel",
      "colorB": 255,
      "colorG": 255,
      "colorR": 255,
      "customProperty": "",
      "flipX": false,
      "flipY": false,
      "height": 640,
      "ignoreSize": false,
      "layoutParameter": null,
      "opacity": 255,
      "positionPercentX": 0,
      "positionPercentY": 0,
      "positionType": 0,
      "rotation": 0,
      "scaleX": 1,
      "scaleY": 1,
      "sizePercentX": 1,
      "sizePercentY": 1,
      "sizeType": 0,
      "tag": 937,
      "touchAble": true,
      "useMergedTexture": false,
      "visible": true,
      "width": 1136,
      "x": 0,
      "y": 0,
      "adaptScreen": false,
      "backGroundImage": null,
      "backGroundImageData": null,
      "backGroundScale9Enable": false,
      "bgColorB": 255,
      "bgColorG": 200,
      "bgColorOpacity": 0,
      "bgColorR": 150,
      "bgEndColorB": 255,
      "bgEndColorG": 200,
      "bgEndColorR": 150,
      "bgStartColorB": 255,
      "bgStartColorG": 255,
      "bgStartColorR": 255,
      "capInsetsHeight": 1,
      "capInsetsWidth": 1,
      "capInsetsX": 0,
      "capInsetsY": 0,
      "clipAble": false,
      "colorType": 1,
      "layoutType": 0,
      "vectorX": 0,
      "vectorY": -0.5
    }
  }
}